spanlp/__init__.py
spanlp/palabrota.py
spanlp/dataset/ARG.txt
spanlp/dataset/BOL.txt
spanlp/dataset/CHL.txt
spanlp/dataset/COL.txt
spanlp/dataset/CRI.txt
spanlp/dataset/CUB.txt
spanlp/dataset/DOM.txt
spanlp/dataset/ECU.txt
spanlp/dataset/ESP.txt
spanlp/dataset/GNQ.txt
spanlp/dataset/GTM.txt
spanlp/dataset/HND.txt
spanlp/dataset/MEX.txt
spanlp/dataset/NIC.txt
spanlp/dataset/PAN.txt
spanlp/dataset/PER.txt
spanlp/dataset/PRI.txt
spanlp/dataset/PRY.txt
spanlp/dataset/SLV.txt
spanlp/dataset/URY.txt
spanlp/dataset/VEN.txt
spanlp/dataset/__init__.py
spanlp/domain/__init__.py
spanlp/domain/constant.py
spanlp/domain/countries.py
spanlp/domain/strategies.py
spanlp/tests/__init__.py
spanlp/tests/test_palabrota.py
spanlp-1.1.0.data/data/data/ARG.txt
spanlp-1.1.0.data/data/data/BOL.txt
spanlp-1.1.0.data/data/data/CHL.txt
spanlp-1.1.0.data/data/data/COL.txt
spanlp-1.1.0.data/data/data/CRI.txt
spanlp-1.1.0.data/data/data/CUB.txt
spanlp-1.1.0.data/data/data/DOM.txt
spanlp-1.1.0.data/data/data/ECU.txt
spanlp-1.1.0.data/data/data/ESP.txt
spanlp-1.1.0.data/data/data/GNQ.txt
spanlp-1.1.0.data/data/data/GTM.txt
spanlp-1.1.0.data/data/data/HND.txt
spanlp-1.1.0.data/data/data/MEX.txt
spanlp-1.1.0.data/data/data/NIC.txt
spanlp-1.1.0.data/data/data/PAN.txt
spanlp-1.1.0.data/data/data/PER.txt
spanlp-1.1.0.data/data/data/PRI.txt
spanlp-1.1.0.data/data/data/PRY.txt
spanlp-1.1.0.data/data/data/SLV.txt
spanlp-1.1.0.data/data/data/URY.txt
spanlp-1.1.0.data/data/data/VEN.txt
spanlp-1.1.0.dist-info/LICENSE
spanlp-1.1.0.dist-info/METADATA
spanlp-1.1.0.dist-info/WHEEL
spanlp-1.1.0.dist-info/top_level.txt
spanlp-1.1.0.dist-info/RECORD
