Metadata-Version: 2.1
Name: spanlp
Version: 1.1.0
Summary: A fast, robust Python library to check for profanity or offensive language in Spanish strings.It contains all the rude words of Spanish-speaking countries (Argentina, Bolivia, Chile, Colombia, Costa Rica, Cuba, Ecuador, El Salvador, España, Guatemala, Guinea Ecuatorial, Honduras, Mexico, Nicaragua, Panama, Paraguay, Peru, Puerto Rico, Dominicana, Uruguay, Venezuela)
Home-page: https://github.com/jfreddypuentes/spanlp
Author: Jhon Freddy Puentes
Author-email: jfredypuentes@gmail.com
License: MIT
Platform: UNKNOWN
Classifier: Intended Audience :: Science/Research
Classifier: Intended Audience :: Developers
Classifier: Intended Audience :: Education
Classifier: License :: OSI Approved :: MIT License
Classifier: Programming Language :: Python
Classifier: Topic :: Software Development
Classifier: Topic :: Scientific/Engineering
Classifier: Development Status :: 5 - Production/Stable
Classifier: Programming Language :: Python :: 3
Classifier: Programming Language :: Python :: 3.6
Classifier: Programming Language :: Python :: 3.7
Classifier: Programming Language :: Python :: 3.8
Classifier: Programming Language :: Python :: 3.9
Classifier: Operating System :: OS Independent
Requires-Python: >=3.6
